<?xml version="1.0" encoding="utf-8"?>
<openerp>
	<data>
		<record model="ir.ui.view" id="payroll_scale_view_inherit">
			<field name="name">hr.salary.scale.view.inherit</field>
			<field name="model">hr.salary.scale</field>
			<field name="type">form</field>
			<field name="inherit_id" ref="hr_payroll_custom.view_salary_scale_form"/>
			<field name="arch" type="xml">
				<xpath expr='//field[@name="employee_type"]' position="after" version="7.0">
					<field name="military_type" />
				</xpath>
			</field>
		</record>
	</data>
</openerp>  