<odoo>
    <data>

        <record id="product_category_form_view_inherit" model="ir.ui.view">
            <field name="name">product category form view</field>
            <field name="model">product.category</field>
            <field name="inherit_id" ref="product.product_category_form_view"/>
            <field name="arch" type="xml">
                <group name="first" position="after">
                    <group name="products_type">
                        <group string="Products Type">
                            <field name="products_type" required="1"/>
                        </group>
                    </group>
                </group>

            </field>
        </record>


        <!--record model="ir.ui.view" id="view_inventory_form_inherit">
            <field name="name">stock.inventory.form.inherit</field>
            <field name="model">stock.inventory</field>
            <field name="inherit_id" ref="stock.view_inventory_form"/>
            <field name="type">form</field>
            <field name="arch" type="xml">

                <xpath expr="//field[@name='state']" position="replace">
                    <field name="state" widget="statusbar" statusbar_visible="draft,confirm"/>
                </xpath>

                <xpath expr="//button[@name='action_start']" position="after">

                    <button name="confirm_inventory" type="object" string="Confirm" states='confirm'
                            class="oe_highlight"
                            groups='stock_custom.group_account_administrator, stock_custom.group_service_manager , stock_custom.group_internal_auditor , stock_custom.group_stock_manager '/>

                    <button name="service_review" type="object" string="Confirm" states='service_review'
                            class="oe_highlight" groups='stock_custom.group_service_manager'/>

                    <button name="account_review" type="object" string="Review" states='account_review'
                            class="oe_highlight" groups='stock_custom.group_account_administrator'/>

                    <button name="cancel_inventory" type="object" string="No approve" class="oe_highlight"
                            attrs="{'invisible': [('state','not in',['service_review','account_review','internal_review'] )] }"/>

                </xpath>

                <xpath expr="//button[@name='action_done']" position="attributes">
                    <attribute name='states'>internal_review</attribute>
                    <attribute name='groups'>stock_custom.group_internal_auditor</attribute>
                    <attribute name='string'>Approve</attribute>
                </xpath>

                <xpath expr="//button[@name='action_start']" position="attributes">
                    <attribute name='groups'>stock_custom.group_account_administrator,
                        stock_custom.group_service_manager , stock_custom.group_internal_auditor ,
                        stock_custom.group_stock_manager
                    </attribute>
                </xpath>

                <xpath expr="//button[@name='action_cancel_draft'][2]" position="replace">
                    <button name="action_cancel_draft" states="confirm,service_review" string="Set to draft"
                            type="object"
                            groups="stock_custom.group_service_manager, stock_custom.group_stock_manager"/>
                </xpath>

                <xpath expr="//button[@name='action_cancel_draft'][1]" position="attributes">
                    <attribute name='invisible'>1</attribute>
                </xpath>

                <xpath expr="//notebook/page/field[@name='line_ids']" position="attributes">
                    <attribute name='attrs'>{'readonly':[('state','not in',['draft','confirm', 'service_review'])]}
                    </attribute>
                </xpath>

            </field>
        </record-->

        <record model="ir.ui.view" id="view_picking_form_inherit">
            <field name="name">stock.picking.form.inherit</field>
            <field name="model">stock.picking</field>
            <field name="inherit_id" ref="stock.view_picking_form"/>
            <field name="type">form</field>
            <field name="arch" type="xml">

                <xpath expr="//field[@name='partner_id']" position="before">
                    <field name='department_id'/>
                </xpath>

                <xpath expr="//field[@name='owner_id']" position="attributes">
                    <attribute name="attrs">{'readonly':[('state','!=','draft')]}</attribute>
                </xpath>

                <xpath expr="//field[@name='company_id']" position="attributes">
                    <attribute name="attrs">{'readonly':[('state','!=','draft')]}</attribute>
                </xpath>

                <xpath expr="//field[@name='scheduled_date']" position="attributes">
                    <attribute name="attrs">{'readonly':[('state','!=','draft')]}</attribute>
                </xpath>

                <xpath expr="//field[@name='origin']" position="attributes">
                    <attribute name="attrs">{'readonly':[('state','!=','draft')]}</attribute>
                </xpath>

                <xpath expr="//field[@name='partner_id']" position="attributes">
                    <attribute name="attrs">{'readonly':[('state','!=','draft')]}</attribute>
                </xpath>

                <xpath expr="//field[@name='move_type']" position="attributes">
                    <attribute name="attrs">{'readonly':[('state','!=','draft')]}</attribute>
                </xpath>

                <xpath expr="//field[@name='priority']" position="attributes">
                    <attribute name="attrs">{'readonly':[('state','!=','draft')]}</attribute>
                </xpath>

                <xpath expr="//notebook/page[2]/field[@name='move_lines']/tree" position="attributes">
                    <attribute name="editable">top</attribute>
                </xpath>

                <xpath expr="//notebook/page[2]/field[@name='move_lines']/tree/field[@name='product_id']" position="attributes">
                    <attribute name="domain">[('type','=','product')]</attribute>
                </xpath>


            </field>
        </record>

        <record model="ir.ui.view" id="view_scrap_form_inherit">
            <field name="name">stock.scrap.form.inherit</field>
            <field name="model">stock.scrap</field>
            <field name="inherit_id" ref="stock.stock_scrap_form_view"/>
            <field name="arch" type="xml">

                <xpath expr="//field[@name='product_uom_id']" position="attributes">
                    <attribute name='readonly'>1</attribute>
                </xpath>


            </field>
        </record>

        <!--record model="ir.ui.view" id="view_scrap_form_inherit">
            <field name="name">stock.scrap.form.inherit</field>
            <field name="model">stock.scrap</field>
            <field name="inherit_id" ref="stock.stock_scrap_form_view"/>
            <field name="type">form</field>
            <field name="arch" type="xml">

                <xpath expr="//button[@name='action_validate']" position="attributes">
                    <attribute name='groups'>stock_custom.group_service_manager</attribute>
                    <attribute name='states'>confirm</attribute>
                    <attribute name='string'>Approve</attribute>
                </xpath>

                <xpath expr="//button[@name='action_validate']" position="before">
                    <button name="confirm_scrap" string="Confirm" type="object" class="oe_highlight" states='draft'
                            groups='stock_custom.group_stock_manager'/>
                </xpath>

                <xpath expr="//button[@name='action_validate']" position="after">
                    <button name="cancel_scrap" string="No Approve" type="object" class="oe_highlight" states='confirm'
                            groups='stock_custom.group_service_manager'/>
                </xpath>

                <xpath expr="//field[@name='state']" position="attributes">
                    <attribute name='statusbar_visible'>draft,confirm</attribute>
                </xpath>


            </field>
        </record-->


        <!--<record id="view_picking_form_inherit" model="ir.ui.view">-->
        <!--<field name="name">Picking Form View</field>-->
        <!--<field name="model">stock.picking</field>-->
        <!--<field name="inherit_id" ref="stock.view_picking_form" />-->
        <!--<field name="arch" type="xml">-->

        <!--<field name="origin" position="after">-->


        <!--</field>-->


        <!--<xpath expr="//button[@name='action_confirm']" position="after">-->
        <!--<button name="confirm" string="Confirm"  class="oe_highlight" type="object"/>-->
        <!--<button name="%(stock_custom.action_stock_create_purchase_requestion)d" id="stock_create_purchase_requestion" string="Create Purchase Requestion" class="oe_highlight" type="action"/>-->
        <!--</xpath>-->
        <!--<xpath expr="//field[@name='move_line_ids']/tree/field[@name='product_id']" position="attributes">-->
        <!--<attribute name="domain">[('categ_id.products_type','=',parent.products_type),('categ_id.products_type','!=',False)]</attribute>-->
        <!--</xpath>-->
        <!--<xpath expr="//field[@name='move_line_ids']/tree/field[@name='product_uom_qty']" position="attributes">-->
        <!--<attribute name="readonly">0</attribute>-->
        <!--</xpath>-->

        <!--</field>-->
        <!--</record>-->


        <record id="view_picking_form_custom" model="ir.ui.view">

            <field name="name">stock.picking.form</field>
            <field name="model">stock.picking</field>
            <field eval="12" name="priority"/>
            <field name="arch" type="xml">
                <form string="Transfer">
                    <header>
                        <field name="order_staionary" invisible="1"/>
                        <field name="order_others" invisible="1"/>

                        <button name="validate_manager"
                                string="Request"
                                type="object"
                                states="draft"
                                class="oe_highlight"
                                groups="stock_custom.group_department_manager"/>

                        <field name="show_st_resp_validate" invisible="1"/>
                        <button name="validate_stock_responsible"
                                string="Confirm"
                                type="object"
                                attrs="{'invisible': ['|',('show_st_resp_validate','!=',True),('state','!=','confirmed')]}"
                                class="oe_highlight"
                                groups="stock_custom.group_stock_manager"/>

                        <!--<button name="do_unreserve"-->
                        <!--string="Unreserve"-->
                        <!--groups="base.group_user"-->
                        <!--type="object"-->
                        <!--states="confirmed"/>-->


                        <field name="id" invisible="1"/>
                        <field name="is_locked" invisible="1"/>
                        <field name="show_mark_as_todo" invisible="1"/>
                        <field name="show_check_availability" invisible="1"/>
                        <field name="show_validate" invisible="1"/>
                        <field name="show_lots_text" invisible="1"/>
                        <!--<button name="action_confirm" attrs="{'invisible': [('show_mark_as_todo', '=', False)]}" string="Mark as Todo" type="object" class="oe_highlight" groups="base.group_user"/>-->
                        <!--<button name="action_assign" attrs="{'invisible': [('show_check_availability', '=', False)]}" string="Check Availability" type="object" class="oe_highlight" groups="stock_custom.group_stock_manager"/>-->
                        <button name="validate_stock"
                                attrs="{'invisible': [('show_check_availability', '=', False)]}"
                                string="Check Availability"
                                type="object"
                                class="oe_highlight"
                                groups="stock_custom.group_stock_manager"/>

                        <button name="create_purchase_requesetion"
                                string="Create Order"
                                groups="stock_custom.group_stock_manager"
                                type="object"

                                attrs="{'invisible': [('order_staionary', '!=', True)]}"
                        />

                        <button name="action_cancel_draft" string="Set to draft"
                            type="object"
                            states="waiting,confirmed"
                            class="btn-primary"
                            confirm="Are you sure you want to make Order Draft?"
                            groups="stock_custom.group_stock_manager"/>

                        <button name="action_cancel_draft"  string="Set to draft" 
                            type="object" 
                            states="assigned"
                            class="btn-primary"
                            confirm="Are you sure you want to make Order Draft?"
                           groups="stock_custom.group_service_manager"/>

                        <button name="create_purchase_requesetion"
                                string="Create Order"
                                type="object"

                                attrs="{'invisible': [('order_others', '!=', True)]}"
                        />

                        <!--<button name="validate_stock_backorder"-->
                        <!--attrs="{'invisible': [('show_check_availability', '=', False)]}"-->
                        <!--string="Validate with Create Back Order"-->
                        <!--type="object"-->
                        <!--class="oe_highlight"-->
                        <!--confirm="Are You Sure you Want To create Backorder with diffrent between Poduct Quntity and Done?!!"-->
                        <!--groups="stock_custom.group_stock_manager"/>-->


                        <button name="button_validate" states="assigned" string="Validate"
                                groups="stock_custom.group_service_manager" type="object" class="oe_highlight"/>
                        <!--<button name="do_print_picking" string="Print" groups="stock.group_stock_user" type="object" attrs="{'invisible': ['|', ('state', 'not in', ('assigned', 'partially_available')), ('is_locked', '=', False)]}"/>-->
                        <!--<button name="%(stock.act_stock_return_picking)d" string="Return" attrs="{'invisible': ['|', ('state', '!=', 'done'), ('is_locked', '=', False)]}" type="action" groups="base.group_user"/>-->
			<button name="action_cancel" states="waiting,confirmed" string="Cancel" confirm="Are you sure you want to cancel Order?"
                                groups="stock_custom.group_stock_manager" type="object"/>                        
			<button name="action_cancel" states="assigned" string="Cancel" confirm="Are you sure you want to cancel Order?"
                                groups="stock_custom.group_service_manager" type="object"/>
                        <field name="picking_type_code" invisible="1"/>
                        <!--<button name="do_unreserve" string="Unreserve" groups="base.group_user" type="object" attrs="{'invisible': ['|', '|', ('picking_type_code', '=', 'incoming'), ('state', 'not in', ('assigned', 'partially_available')), ('is_locked', '=', False)]}"/>-->
                        <field name="show_operations" invisible="1" readonly="1"/>
                        <field name="move_line_exist" invisible="1"/>
                        <field name="has_packages" invisible="1"/>
                        <!--<button name="button_scrap" type="object" string="Scrap" attrs="{'invisible': ['|', '|', '&amp;', ('picking_type_code', '!=', 'incoming'), ('state', 'in', ('draft', 'cancel', 'waiting')), '&amp;', ('picking_type_code', '=', 'incoming'), ('state', '!=', 'done'), ('is_locked', '=', False)]}"/>-->
                        <!--<button name="action_toggle_is_locked" attrs="{'invisible': ['|', ('state', 'in', ('draft','cancel')), ('is_locked', '=', False)]}" string="Unlock" groups="stock.group_stock_manager" type="object" help="If the picking is unlocked you can edit initial demand (for a draft picking) or done quantities (for a done picking)."/>-->
                        <!--<button name="action_toggle_is_locked" attrs="{'invisible': [('is_locked', '=', True)]}" string="Lock" class="oe_highlight" groups="stock.group_stock_manager" type="object"/>-->
                        <field name="state" widget="statusbar"
                               statusbar_visible="draft,confirmed,partially_available,assigned,done"/>
                        <field name="picking_type_entire_packs" invisible="1"/>
                    </header>
                    <sheet>
                        <div class="oe_button_box" name="button_box">
                            <field name="has_scrap_move" invisible="True"/>
                            <field name="has_tracking" invisible="True"/>
                            <button name="action_see_move_scrap" string="Scraps" type="object"
                                    class="oe_stat_button" icon="fa-arrows-v"
                                    attrs="{'invisible': [('has_scrap_move', '=', False)]}"/>
                            <button name="action_see_packages" string="Packages" type="object"
                                    class="oe_stat_button" icon="fa-cubes"
                                    attrs="{'invisible': [('has_packages', '=', False)]}"/>
                            <button name="%(stock.action_stock_report)d"
                                    attrs="{'invisible': ['|', ('state', '!=', 'done'), ('has_tracking', '=', False)]}"
                                    icon="fa-arrow-up" class="oe_stat_button" string="Up/Down Traceability"
                                    type="action" groups="stock.group_production_lot"/>
                        </div>
                        <h1 class="hidden-xs">
                            <field name="name" attrs="{'invisible': [('name','=','/')]}" readonly="1"/>
                        </h1>
                        <group>
                            <group>
                                <field name="partner_id" invisible="1"
                                       attrs="{'readonly': [('state', '!=', 'draft')]}"/>
                                <field name="user_id"/>
                                <field name="picking_type_id" domain="[('code','=','outgoing')]"
                                       attrs="{'readonly': [('state', '!=', 'draft')]}"/>
                                <field name="location_id" groups="stock.group_stock_multi_locations"
                                       attrs="{'invisible': [('picking_type_code', '=', 'outgoing')]}"/>
                                <field name="location_dest_id" groups="stock.group_stock_multi_locations"
                                       attrs="{'invisible': [('picking_type_code', '=', 'incoming')]}"/>

                                <!--<field name="backorder_id" readonly="1"-->
                                <!--attrs="{'invisible': [('backorder_id','=',False)]}"/>-->
                                <field name="purchase_requisition_id"
                                       attrs="{'invisible':[('purchase_requisition_id','=',False)]}"/>
                                <field name="back_order_id" attrs="{'invisible':[('back_order_id','=',False)]}"
				 context="{'form_view_ref': 'stock_custom.view_picking_form_custom'}"/>
                            </group>
                            <group>
                                <field name="department_id"/>
                                <field name="scheduled_date"
                                       attrs="{'readonly': ['|',('id', '=', False),('state','!=','draft')], 'required': [('id', '!=', False)]}"/>
                                <!--<field name="origin" placeholder="e.g. PO0032" attrs="{'readonly': [('state', '!=', 'draft')]}"/>-->

                                <field name="products_type" required="1" attrs="{'readonly': [('state', '!=', 'draft')]}"/>

                                <field name="owner_id" groups="stock.group_tracking_owner"/>
                                <div groups="stock.group_tracking_owner" colspan="2" col="2">
                                    <button name="action_assign_owner" string="Assign Owner" type="object"
                                            attrs="{'invisible': ['|',('move_line_exist', '=', False),('state', 'not in', ('draft','assigned','confirmed'))]}"
                                            class="oe_link"/>
                                </div>
                            </group>
                        </group>
                        <notebook>
                            <page string="Detailed Operations" attrs="{'invisible': [('show_operations', '=', False)]}">
                                <field name="move_line_ids"
                                       attrs="{'readonly': [('state', '=', 'done'), ('is_locked', '=', True)]}"
                                       context="{'default_picking_id': id, 'default_location_id': location_id, 'default_location_dest_id': location_dest_id}">
                                    <tree editable="top" decoration-muted="(state == 'done' and is_locked == True)"
                                          decoration-danger="qty_done&gt;product_uom_qty and state!='done'"
                                          decoration-success="qty_done==product_uom_qty and state!='done' and not result_package_id">
                                        <field name="product_id" required="1"
                                               attrs="{'readonly': ['|', ('state', '=', 'done'), ('move_id', '!=', False)]}"/>
                                        <field name="move_id" invisible="1"/>
                                        <field name="in_entire_package" invisible="1"/>
                                        <field name="product_uom_id" force_save="1"
                                               attrs="{'readonly': [('state', '!=', 'draft')]}"
                                               groups="product.group_uom"/>
                                        <field name="package_id"
                                               attrs="{'readonly': [('in_entire_package', '=', True)]}"
                                               groups="stock.group_tracking_lot"
                                               domain="[('location_id', '=', location_id)]"/>
                                        <field name="location_id"
                                               attrs="{'readonly': [('in_entire_package', '=', True)]}"
                                               groups="stock.group_stock_multi_locations,stock.group_tracking_lot"
                                               domain="[('id', 'child_of', parent.location_id)]"/>
                                        <field name="location_dest_id"
                                               attrs="{'readonly': [('in_entire_package', '=', True)]}"
                                               groups="stock.group_stock_multi_locations,stock.group_tracking_lot"
                                               domain="[('id', 'child_of', parent.location_dest_id)]"/>
                                        <field name="result_package_id"
                                               attrs="{'readonly': [('in_entire_package', '=', True)]}"
                                               groups="stock.group_tracking_lot"
                                               domain="['|', '|', ('location_id', '=', False), ('location_id', '=', location_dest_id), ('id', '=', package_id)]"/>
                                        <field name="lots_visible" invisible="1"/>
                                        <field name="owner_id" groups="stock.group_tracking_owner"/>
                                        <field name="state" invisible="1"/>
                                        <field name="lot_id" groups="stock.group_production_lot"
                                               attrs="{'column_invisible': [('parent.show_lots_text', '=', True)], 'invisible': [('lots_visible', '=', False)], 'readonly': [('in_entire_package', '=', True)]}"
                                               domain="[('product_id', '=', product_id)]"
                                               context="{'default_product_id': product_id}"/>
                                        <field name="lot_name" groups="stock.group_production_lot"
                                               attrs="{'column_invisible': [('parent.show_lots_text', '=', False)], 'invisible': [('lots_visible', '=', False)], 'readonly': [('in_entire_package', '=', True)]}"
                                               context="{'default_product_id': product_id}"/>
                                        <field name="is_initial_demand_editable" invisible="1"/>
                                        <field name="product_uom_qty" readonly="1"/>
                                        <field name="is_locked" invisible="1"/>
                                        <field name="qty_done"
                                               attrs="{'readonly': ['|', ('state', 'in', ('done', 'cancel')), ('is_locked', '=', True), ('in_entire_package', '=', True)]}"
                                               force_save="1"/>
                                    </tree>
                                </field>
                                <field name="entire_package_detail_ids"
                                       context="{'picking_id': id, 'tree_view_ref': 'stock.view_quant_package_picking_tree'}"
                                       attrs="{'invisible': ['|', ('picking_type_entire_packs', '=', False), ('show_operations', '=', False)]}"
                                       readonly="0"/>
                                <button class="oe_highlight" name="put_in_pack" type="object" string="Put in Pack"
                                        attrs="{'invisible': [('state', 'in', ('done', 'cancel'))]}"
                                        groups="stock.group_tracking_lot"/>
                            </page>
                            <page string="Operations">
                                <field name="id" invisible="1"/>
                                <field name="move_lines"
                                       attrs="{'readonly': ['|', '&amp;', ('show_operations', '=', True), '|', ('is_locked', '=', True), ('state', '=', 'done'), '&amp;', ('state', '=', 'done'), ('is_locked', '=', True)]}"
                                       context="{'picking_type_code': picking_type_code, 'default_picking_id': id, 'form_view_ref':'stock.view_move_picking_form', 'address_in_id': partner_id, 'default_picking_type_id': picking_type_id, 'default_location_id': location_id, 'default_location_dest_id': location_dest_id}">
                                    <tree decoration-danger="state != 'done' and quantity_done > reserved_availability and show_reserved_availability"
                                          decoration-muted="scrapped == True or state == 'cancel' or (state == 'done' and is_locked == True)"
                                          string="Stock Moves" editable="bottom">
                                        <field name="name" invisible="1"/>
                                        <field name="date_expected" invisible="1"/>
                                        <field name="state" invisible="1" readonly="0"/>
                                        <field name="picking_type_id" invisible="1"/>
                                        <field name="location_id" invisible="1"/>
                                        <field name="location_dest_id" invisible="1"/>
                                        <field name="scrapped" invisible="1"/>
                                        <field name="picking_code" invisible="1"/>
                                        <field name="product_type" invisible="1"/>
                                        <field name="show_details_visible" invisible="1"/>
                                        <field name="show_reserved_availability" invisible="1"/>
                                        <field name="show_operations" invisible="1" readonly="1"/>
                                        <field name="additional" invisible="1"/>
                                        <field name="has_move_lines" invisible="1"/>
                                        <field name="is_locked" invisible="1"/>
                                        <field name="product_id"
                                               domain="[('categ_id.products_type','=',parent.products_type),('categ_id.products_type','!=',False),('type','=','product')]"
                                               required="1"
                                               attrs="{'readonly': ['|', '&amp;', ('state', '!=', 'draft'), ('additional', '=', False), ('has_move_lines', '=', True)]}"/>
                                        <field name="is_initial_demand_editable" invisible="1"/>
                                        <field name="is_quantity_done_editable" invisible="1"/>
                                        <field name="product_uom_qty" string="Initial Demand"
                                               attrs="{'readonly': [('parent.state', 'not in', ('draft'))]}"/>
                                        <field name="reserved_availability" string="Reserved"
                                               attrs="{'column_invisible': ['|', ('parent.state','=', 'done'), ('parent.picking_type_code', '=', 'incoming')]}"/>
                                        <field name="quantity_done" string="Done"
                                               attrs="{'readonly': [('parent.state', 'not in', ('waiting','confirmed'))]}"/>
                                        <field name="product_uom"
                                               attrs="{'readonly': [('state', '!=', 'draft'), ('additional', '=', False)]}"
                                               options="{'no_open': True, 'no_create': True}" string="Unit of Measure"
                                               groups="product.group_uom"/>
                                        <button name="action_show_details" string="Register lots, packs, location"
                                                type="object" icon="fa-list"
                                                attrs="{'invisible': [('show_details_visible', '=', False)]}"
                                                options='{"warn": true}'/>
                                    </tree>
                                </field>
                                <field name="entire_package_ids"
                                       context="{'picking_id': id, 'tree_view_ref': 'stock.view_quant_package_picking_tree'}"
                                       attrs="{'invisible': ['|', ('picking_type_entire_packs', '=', False), ('show_operations', '=', True)]}"
                                       readonly="0"/>
                                <button class="oe_highlight" name="put_in_pack" type="object" string="Put in Pack"
                                        attrs="{'invisible': [('state', 'in', ('done', 'cancel'))]}"
                                        groups="stock.group_tracking_lot"/>
                            </page>

                            <page string="Note" name="note">
                                 <field name="note" placeholder="write your note"/>
                            </page> 

                            <page string="Additional Info" invisible="1" name="extra">
                                <group>
                                    <group>
                                        <field name="picking_type_code" invisible="1"/>
                                        <!--<field name="move_type"-->
                                        <!--attrs="{'invisible': [('picking_type_code', '=', 'incoming')],'readonly': [('state', '!=', 'draft')]}"/>-->
                                        <!--<field name="picking_type_id" domain="[('code','=','outgoing')]"-->
                                        <!--attrs="{'readonly': [('state', '!=', 'draft')]}"/>-->
                                    </group>
                                    <group>
                                        <field name="company_id" groups="base.group_multi_company"
                                               options="{'no_create': True}"/>
                                        <!--<field name="group_id" groups="base.group_no_one"/>-->
                                        <!--<field name="priority"-->
                                        <!--attrs="{'invisible': [('picking_type_code', '=', 'incoming')],'readonly': [('state', '!=', 'draft')]}"/>-->
                                    </group>
                                </group>
                            </page>

                        </notebook>
                    </sheet>
                    <div class="oe_chatter">
                        <field name="message_follower_ids" widget="mail_followers"/>
                        <field name="activity_ids" widget="mail_activity"/>
                        <field name="message_ids" widget="mail_thread"/>
                    </div>
                </form>
            </field>
        </record>


        <record model="ir.ui.view" id="view_picking_tree_custom">
            <field name="name">Stock Operation</field>
            <field name="model">stock.picking</field>
            <field name="arch" type="xml">
                <tree string="Operation Types">
                    <field name="name"/>
                    <field name="state"/>

                </tree>
            </field>
        </record>


        <record id="stock_picking_action_custom" model="ir.actions.act_window">
            <field name="name">Stock Picking</field>
            <field name="res_model">stock.picking</field>
	    <field name="domain">[('is_outgoing_order','=',True)]</field>
            <field name="view_type">form</field>
            <field name="view_mode">tree,form</field>
        </record>


        <record id="action_view_picking_tree_custom" model="ir.actions.act_window.view">
            <field eval="2" name="sequence"/>
            <field name="view_mode">tree</field>
            <field name="view_id" ref="view_picking_tree_custom"/>
            <field name="act_window_id" ref="stock_picking_action_custom"/>
        </record>

        <record id="action_view_picking_form_custom" model="ir.actions.act_window.view">
            <field eval="3" name="sequence"/>
            <field name="view_mode">form</field>
            <field name="view_id" ref="view_picking_form_custom"/>
            <field name="act_window_id" ref="stock_picking_action_custom"/>
        </record>

        <menuitem id="all_picking_custom"
                  name="Outgoing Order"
                  parent="stock.menu_stock_warehouse_mgmt"
                  sequence="6"
                  action="stock_picking_action_custom"
                  groups="stock.group_stock_manager,stock.group_stock_user,stock_custom.group_department_manager,stock_custom.group_stock_manager,stock_custom.group_service_manager"

        />


        <!--Landed Cost View-->

        <record model="ir.ui.view" id="view_stock_landed_cost_form_inherit">
            <field name="name">stock.landed.cost.form.inherit</field>
            <field name="model">stock.landed.cost</field>
            <field name="inherit_id" ref="stock_landed_costs.view_stock_landed_cost_form"/>
            <field name="arch" type="xml">
                <xpath expr="//field[@name='state']" position="attributes">
                    <attribute name="statusbar_visible">draft,validated,done</attribute>
                </xpath>
                <xpath expr="//button[@name='button_validate']" position="attributes">
                    <attribute name="states">validated</attribute>
                    <attribute name="groups">stock_custom.group_service_manager</attribute>
                </xpath>
                <xpath expr="//button[@name='button_cancel']" position="attributes">
                    <attribute name="string">Reject</attribute>
                </xpath>

                <xpath expr="//button[@name='button_cancel']" position="attributes">
                    <attribute name="states">validated</attribute>
                    <attribute name="groups">stock_custom.group_service_manager</attribute>
                </xpath>
                <xpath expr="//button[@name='button_validate']" position="after">
                    <button name="stock_responible_validate" string="Validate Stock Responsible" type="object"
                            states="draft" groups="stock_custom.group_stock_manager" class="oe_highlight"/>
                </xpath>
                <xpath expr="//field[@name='picking_ids']" position="attributes">
                    <attribute name="required">1</attribute>
                </xpath>
            </field>
        </record>

        <!-- Inventory Valuation View -->

        <record model="ir.ui.view" id="view_stock_product_tree2_inherit">
            <field name="name">product.stock.tree.2.inherit</field>
            <field name="model">product.product</field>
            <field name="inherit_id" ref="stock_account.view_stock_product_tree2" />
            <field name="arch" type="xml">
                <xpath expr="//tree" position="attributes">
                    <attribute name="create">false</attribute>
                </xpath>
            </field>
        </record>


        <!--record model="ir.ui.view" id="view_inventory_form_inherit">
            <field name="name">stock.inventory.form.inherit</field>
            <field name="model">stock.inventory</field>
            <field name="inherit_id" ref="stock.view_inventory_form"/>
            <field name="type">form</field>
            <field name="arch" type="xml">

                <xpath expr="//field[@name='state']" position="replace">
                    <field name="state" widget="statusbar" statusbar_visible="draft,confirm"/>
                </xpath>

                <xpath expr="//button[@name='action_start']" position="after">

                    <button name="confirm_inventory" type="object" string="Confirm" states='confirm'
                            class="oe_highlight"
                            groups='stock_custom.group_account_administrator, stock_custom.group_service_manager , stock_custom.group_internal_auditor , stock_custom.group_stock_manager '/>

                    <button name="service_review" type="object" string="Confirm" states='service_review'
                            class="oe_highlight" groups='stock_custom.group_service_manager'/>

                    <button name="account_review" type="object" string="Review" states='account_review'
                            class="oe_highlight" groups='stock_custom.group_account_administrator'/>

                    <button name="cancel_inventory" type="object" string="No approve" class="oe_highlight"
                            attrs="{'invisible': [('state','not in',['service_review','account_review','internal_review'] )] }"/>

                </xpath>

                <xpath expr="//button[@name='action_done']" position="attributes">
                    <attribute name='states'>internal_review</attribute>
                    <attribute name='groups'>stock_custom.group_internal_auditor</attribute>
                    <attribute name='string'>Approve</attribute>
                </xpath>

                <xpath expr="//button[@name='action_start']" position="attributes">
                    <attribute name='groups'>stock_custom.group_account_administrator,
                        stock_custom.group_service_manager , stock_custom.group_internal_auditor ,
                        stock_custom.group_stock_manager
                    </attribute>
                </xpath>

                <xpath expr="//button[@name='action_cancel_draft'][2]" position="replace">
                    <button name="action_cancel_draft" states="confirm,service_review" string="Set to draft"
                            type="object"
                            groups="stock_custom.group_service_manager, stock_custom.group_stock_manager"/>
                </xpath>

                <xpath expr="//button[@name='action_cancel_draft'][1]" position="attributes">
                    <attribute name='invisible'>1</attribute>
                </xpath>

                <xpath expr="//notebook/page/field[@name='line_ids']" position="attributes">
                    <attribute name='attrs'>{'readonly':[('state','not in',['draft','confirm', 'service_review'])]}
                    </attribute>
                </xpath>

            </field>
        </record-->

        <!--record model="ir.ui.view" id="view_picking_form_inherit">
            <field name="name">stock.picking.form.inherit</field>
            <field name="model">stock.picking</field>
            <field name="inherit_id" ref="stock.view_picking_form"/>
            <field name="type">form</field>
            <field name="arch" type="xml">

                <xpath expr="//field[@name='partner_id']" position="before">
                    <field name='department_id'/>
                </xpath>

            </field>
        </record-->

        <!--record model="ir.ui.view" id="view_scrap_form_inherit">
            <field name="name">stock.scrap.form.inherit</field>
            <field name="model">stock.scrap</field>
            <field name="inherit_id" ref="stock.stock_scrap_form_view"/>
            <field name="type">form</field>
            <field name="arch" type="xml">

                <xpath expr="//button[@name='action_validate']" position="attributes">
                    <attribute name='groups'>stock_custom.group_service_manager</attribute>
                    <attribute name='states'>confirm</attribute>
                    <attribute name='string'>Approve</attribute>
                </xpath>

                <xpath expr="//button[@name='action_validate']" position="before">
                    <button name="confirm_scrap" string="Confirm" type="object" class="oe_highlight" states='draft'
                            groups='stock_custom.group_stock_manager'/>
                </xpath>

                <xpath expr="//button[@name='action_validate']" position="after">
                    <button name="cancel_scrap" string="No Approve" type="object" class="oe_highlight" states='confirm'
                            groups='stock_custom.group_service_manager'/>
                </xpath>

                <xpath expr="//field[@name='state']" position="attributes">
                    <attribute name='statusbar_visible'>draft,confirm</attribute>
                </xpath>


            </field>
        </record-->

          <!-- inherit stock_warehouse view -->
          <record id="stock_warehouse_view_inherit" model="ir.ui.view">
            <field name="name">stock warehouse form view</field>
            <field name="model">stock.warehouse</field>
            <field name="inherit_id" ref="stock.view_warehouse"/>
            <field name="arch" type="xml">

                <xpath expr="//field[@name='partner_id']" position="attributes">
                    <attribute name="required">1</attribute>
                </xpath>
            </field>
        </record>


        <!-- add logistics data to stock admin group -->

        <record id="view_template_property_form_inherit_stock_custom" model="ir.ui.view">
            <field name="name">product.template.stock.custom.property.form.inherit</field>
            <field name="model">product.template</field>
            <field name="inherit_id" ref="stock.view_template_property_form"/>
            <field name="arch" type="xml">
                <xpath expr="//group[@name='group_lots_and_weight']" position="attributes">
                    <attribute name="groups">stock_custom.group_stock_admin</attribute>
                </xpath>
            </field>
        </record>

        <record id="view_location_form_inherit_stock_custom" model="ir.ui.view">
            <field name="name">stock.location.form</field>
            <field name="model">stock.location</field>
            <field name="inherit_id" ref="stock.view_location_form" />
            <field name="arch" type="xml">
                <xpath expr="//form/group/group[4]" position="attributes">
                    <attribute name="groups">stock_custom.group_stock_admin</attribute>
                </xpath>
            </field>
        </record>
     
        <record id="product_category_form_view_inherit_stock_custom" model="ir.ui.view">
            <field name="name">product.category.form</field>
            <field name="model">product.category</field>
            <field name="inherit_id" ref="stock.product_category_form_view_inherit" />
            <field name="arch" type="xml">
                <xpath expr="//group[2]" position="attributes">
                    <attribute name="groups">stock_custom.group_stock_admin</attribute>
                </xpath>
            </field>
        </record>
 
        <record model="ir.ui.view" id="view_picking_type_form_inherit_stock_custom">
            <field name="name">Operation Types</field>
            <field name="model">stock.picking.type</field>
            <field name="inherit_id" ref="stock.view_picking_type_form" />
            <field name="arch" type="xml">
                <xpath expr="//form/sheet/group[2]/group[2]" position="attributes">
                    <attribute name="groups">stock_custom.group_stock_manager</attribute>
                </xpath>
            </field>
        </record>
    
        <!-- add stock admin group to some views -->

        <menuitem id="stock.menu_package" name="Packages" parent="stock.menu_stock_inventory_control" action="stock.action_package_view" groups="stock.group_tracking_lot,stock_custom.group_stock_admin" sequence="102"/>

        <menuitem
            id="stock.menu_reordering_rules_config"
            action="stock.action_orderpoint_form"
            name="Reordering Rules" parent="stock.menu_stock_inventory_control" groups="stock_custom.group_stock_admin" sequence="10"/>

        <menuitem action="stock.action_procurement_compute" id="stock.menu_procurement_compute" parent="stock.menu_stock_warehouse_mgmt" groups="stock_custom.group_stock_admin" sequence="135"/>

        <menuitem id="stock.menu_routes_config" action="stock.action_routes_form" name="Routes" parent="stock.menu_warehouse_config" sequence="3" groups="stock.group_adv_location,stock_custom.group_stock_admin"/>

        <menuitem id="stock.menu_product_packagings" name="Product Packages" parent="stock.menu_product_in_config_stock" action="product.action_packaging_view" groups="product.group_stock_packaging,stock_custom.group_stock_admin"/>


    </data>
</odoo>
