<?xml version="1.0" encoding="UTF-8" ?>
<odoo>
    <data>

        <report id="iban_alsabil_report_action"
                string="Iban Alsabil Study Ornick"
                model="zakat.dzc8"
                report_type="qweb-pdf"
                file="dzc_8.iban_alsabil_report"
                name="dzc_8.iban_alsabil_report"
                attachment_use="False"
                menu="True"
        />

        <record id="dzc_8.iban_alsabil_report_action" model="ir.actions.report">
            <field name="paperformat_id" ref="zakat_base.zakat_paprFormat"/>
        </record>

        <!-- Transport Companies report-->

         <report id="transport_company_report_action"
                string="Transport Companies Report"
                model="dzc8.transport.company"
                report_type="qweb-pdf"
                file="dzc_8.transport_companies_report"
                name="dzc_8.transport_companies_report"
                attachment_use="False"
                menu="True"
        />

        <record id="dzc_8.transport_company_report_action" model="ir.actions.report">
            <field name="paperformat_id" ref="zakat_base.zakat_paprFormat"/>
        </record>

            <!-- iban alsabil payment report  -->
            <report id="iban_alsabil_payment_action_report"
            string="Iban Alsabil Payment"
            model="zakat.dzc8.payment"
            report_type="qweb-pdf"
            file="dzc_8.iban_alsabil_payment_report"
            name="dzc_8.iban_alsabil_payment_report"
            attachment_use="False"
            menu="True" />

         <record id="dzc_8.iban_alsabil_payment_action_report" model="ir.actions.report">
            <field name="paperformat_id" ref="zakat_base.zakat_paprFormat"/>
        </record>

    </data>
</odoo>